[
  {
    "modtime": "01-11-2024 15:55",
    "filename": "/devops/aws-notes/readme",
    "title": "AWS Notes",
    "category": "devops"
  },
  {
    "modtime": "01-11-2024 15:55",
    "filename": "/devops/aws-notes/ec2",
    "title": "EC2 Notes",
    "category": "devops"
  },
  {
    "modtime": "01-10-2024 12:36",
    "filename": "/coding/pytorch/readme",
    "title": "Pytorch Learning Notes",
    "category": "coding"
  },
  {
    "modtime": "01-10-2024 12:31",
    "filename": "/coding/python/readme",
    "title": "Python notes index",
    "category": "coding"
  },
  {
    "modtime": "01-10-2024 11:56",
    "filename": "/coding/deeplearning",
    "title": "Deep learning notes",
    "category": "coding"
  },
  {
    "modtime": "01-09-2024 15:58",
    "filename": "/coding/python/python-tutorial/python-tutorial",
    "title": "Python Tutorial",
    "category": "coding"
  },
  {
    "modtime": "01-09-2024 14:14",
    "filename": "/coding/blockchain/blockchain-roadmap",
    "title": "Roadmap blockchain",
    "category": "coding"
  },
  {
    "modtime": "01-04-2024 10:11",
    "filename": "/self/self/dreams",
    "title": "My dreams",
    "category": "self"
  },
  {
    "modtime": "01-04-2024 09:59",
    "filename": "/devops/k8s2/k8s-doc/01.architecture",
    "title": "Kubernetes Architecture",
    "category": "devops"
  },
  {
    "modtime": "01-03-2024 18:04",
    "filename": "/devops/linux/archlinux",
    "title": "Arch Linux Notes",
    "category": "devops"
  }
]
